qsrs-2.0.0.dist-info/METADATA
qsrs-2.0.0.dist-info/WHEEL
qsrs/__init__.py
qsrs/qsrs.abi3.so
qsrs-2.0.0.dist-info/RECORD
