Metadata-Version: 2.1
Name: qsrs
Version: 2.0.0.post2
Classifier: Programming Language :: Python
Classifier: Programming Language :: Rust
Classifier: Programming Language :: Python :: 3.7
Classifier: Programming Language :: Python :: 3.8
Classifier: Programming Language :: Python :: 3.9
Classifier: Development Status :: 5 - Production/Stable
Classifier: Intended Audience :: Science/Research
Classifier: Topic :: Software Development :: Compilers
Author: Ethan Smith <ethanhs@berkeley.edu>
Author-email: Ethan Smith <ethanhs@berkeley.edu>
License: LGPL-2.1 AND BSD-3-Clause
